[
 {
    "question": "關於西元1971年於甘肅武威縣旱灘坡發掘出土醫藥簡牘武威漢簡之敘述，下列何者錯誤？",
    "options": {
      "A": "該掘出土武威漢簡之漢墓屬於東漢早期之古墓",
      "B": "武威漢簡《治百病方》中已初步運用了辨證論治的原則",
      "C": "簡牘記述了針灸穴位和針灸禁忌等內容",
      "D": "簡牘中藥物仍未以複方形式出現"
    },
    "answer": "D",
    "category": "中醫史"
  },
  {
    "question": "依《周禮．天官冢宰》，下列何者非為當時醫政組織設官分職之屬？",
    "options": {
      "A": "食醫",
      "B": "瘍醫",
      "C": "疾醫",
      "D": "乳醫"
    },
    "answer": "D",
    "category": "中醫史"
  },
  {
    "question": "關於《新修本草》之敘述，下列何者錯誤？",
    "options": {
      "A": "宋嘉祐三年，政府收集了全國150多州郡的標本和藥圖，由蘇頌等人研究整理，並於嘉祐六年編成",
      "B": "其爲中國歷史上由政府頒行的第一部藥典",
      "C": "其包括正經二十卷、藥圖二十五卷、圖經七卷，加上目錄二卷",
      "D": "原書已近亡佚，僅部分殘存，但因後世本草書和方劑書的轉引，其內容基本上被保留下來"
    },
    "answer": "A",
    "category": "中醫史"
  },
  {
    "question": "宋元時期，中日兩國民間貿易往來中藥物佔有重要的地位，當時日本輸入中國以下列何種藥物為大宗？",
    "options": {
      "A": "硫磺",
      "B": "丁香",
      "C": "真珠",
      "D": "薔薇水"
    },
    "answer": "A",
    "category": "中醫史"
  },
  {
    "question": "金元四大家的醫學思想影響東亞。日本田代三喜留華十二年後創立「某甲學社」；朝鮮《醫方類聚》收錄大量「某乙」醫論與方劑。關於某甲、某乙，下列何者正確？",
    "options": {
      "A": "甲：丹溪，乙：東垣",
      "B": "甲：東垣，乙：丹溪",
      "C": "甲：易水，乙：完素",
      "D": "甲：完素，乙：易水"
    },
    "answer": "A",
    "category": "中醫史"
  },
  {
    "question": "那位醫家擅長以「通」、「清」、「宣」處理外感熱病？",
    "options": {
      "A": "李中梓",
      "B": "薛立齋",
      "C": "王肯堂",
      "D": "劉守真"
    },
    "answer": "D",
    "category": "中醫史"
  },
  {
    "question": "徐靈胎為清代名醫，有關他的資料下列敘述何者錯誤？",
    "options": {
      "A": "博聞好學，少年習儒，後因家人罹疾而逝，發憤讀醫",
      "B": "勤於著述，著作頗多，主要內容為註解及重編歷代典籍",
      "C": "其第一部著作是《難經經釋》，運用《內經》的基本理論來解釋《難經》條文",
      "D": "徐氏尚兼通天文、地理、數學、水利、文詞、音樂等"
    },
    "answer": "B",
    "category": "中醫史"
  },
  {
    "question": "下列何人曾擔任中醫史上第一本專業醫學雜誌《吳醫彙講》的刊行主編？",
    "options": {
      "A": "唐大烈",
      "B": "承澹盫",
      "C": "惲鐵樵",
      "D": "時逸人"
    },
    "answer": "A",
    "category": "中醫史"
  },
  {
    "question": "先秦出現經脈概念，而後完成十二經脈理論。下列那一脈最後出現？",
    "options": {
      "A": "手厥陰心包絡",
      "B": "足太陽膀胱",
      "C": "手少陽三焦",
      "D": "手太陰肺"
    },
    "answer": "A",
    "category": "中醫史"
  },
  {
    "question": "根據聯合國世界記憶工程計畫，東亞傳統醫藥典籍已經有多本收入裏頭，包含中國《本草綱目》、韓國《東醫寶鑑》，2011年下列那一部《漢書．藝文志》出現的經典收錄於世界記憶工程計畫名錄？",
    "options": {
      "A": "《黃帝內經》",
      "B": "《千金要方》",
      "C": "《醫心方》",
      "D": "《甲乙經》"
    },
    "answer": "A",
    "category": "中醫史"
  },
  {
    "question": "飲食失調可能會傷害身體，導致疾病，在《素問．生氣通天論》的敘述何者錯誤？",
    "options": {
      "A": "味過於酸，肝氣以津，脾氣乃絕",
      "B": "味過於鹹，大骨氣勞，短肌，心氣抑",
      "C": "味過於甘，肺氣喘滿，色黑，腎氣不衡",
      "D": "味過於苦，脾氣不濡，胃氣乃厚"
    },
    "answer": "C",
    "category": "內經"
  },
  {
    "question": "陰陽的變化，《內經》採用取象比類，以天例人的方法來說明陰陽在人體生理現象，下列敘述何者錯誤？",
    "options": {
      "A": "濁陰出下竅",
      "B": "清陽實四肢",
      "C": "清陽發腠理",
      "D": "清陽實臟腑"
    },
    "answer": "D",
    "category": "內經"
  },
  {
    "question": "關於五行對應於情志之敘述，以及五行生剋乘侮之規律，下列何者正確？",
    "options": {
      "A": "悲盛侮怒",
      "B": "過喜剋恐",
      "C": "思不及則恐乘之",
      "D": "過恐反侮思"
    },
    "answer": "D",
    "category": "中醫基礎理論"
  },
  {
    "question": "依據《難經．第三難》，尺脈太盛，因而上乘寸部之陽位，在「陰陽相乘，有覆有溢」理論中，此脈象之成因，下列何者正確？",
    "options": {
      "A": "陽乘陰，外關內格",
      "B": "陰乘陽，外關內格",
      "C": "陽乘陰，內關外格",
      "D": "陰乘陽，內關外格"
    },
    "answer": "B",
    "category": "難經"
  },
  {
    "question": "《靈樞．決氣》人有六氣之名稱，但實質上為一氣之所化，此六氣之名，下列何者錯誤？",
    "options": {
      "A": "氣",
      "B": "精",
      "C": "脈",
      "D": "神"
    },
    "answer": "D",
    "category": "內經"
  },
  {
    "question": "五行應用在臨床治療中，《難經．七十五難》中，對於「東方實西方虛」之證，下列治法何者正確？",
    "options": {
      "A": "瀉金補木",
      "B": "瀉水補金",
      "C": "瀉木補土",
      "D": "瀉火補水"
    },
    "answer": "D",
    "category": "難經"
  },
  {
    "question": "下列有關養生的法則何者正確？",
    "options": {
      "A": "不務快其心",
      "B": "不時御神",
      "C": "不知持滿",
      "D": "逆於生樂"
    },
    "answer": "A",
    "category": "中醫基礎理論"
  },
  {
    "question": "依《素問．四氣調神大論》所記載的四時養生方法，其中「夜臥早起，廣步於庭，被髮緩形」，為何季節的養生法？",
    "options": {
      "A": "夏",
      "B": "冬",
      "C": "春",
      "D": "秋"
    },
    "answer": "C",
    "category": "內經"
  },
  {
    "question": "依《素問．六微旨大論》有關升降出入之敘述，下列共幾項正確？①出入廢則神機化滅，升降息則氣立孤危 ②非出入，則無以生長化收藏；非升降，則無以生長壯老已 ③是以升降出入，無器不有。故器者生化之宇，器散則分之，生化息矣 ④故無不出入，無不升降。化有小大，期有近遠",
    "options": {
      "A": "1",
      "B": "2",
      "C": "3",
      "D": "4"
    },
    "answer": "C",
    "category": "內經"
  },
  {
    "question": "85歲病患因阻塞性中風已臥床3個月，近日左臀部長出疔瘡，1週內迅速發展為癰並已化膿，經外科手術清創後，癰膿尚未深及骨頭。依據《靈樞．癰疽》中所敘述形成癰之過程，與下列何者無直接關係？",
    "options": {
      "A": "營氣",
      "B": "衛氣",
      "C": "津液",
      "D": "寒邪"
    },
    "answer": "C",
    "category": "內經"
  },
   {
    "question": "依《靈樞．本輸篇》提到內臟相互間的關係，下列何臟腑上連肺，又與三焦聯繫？",
    "options": {
      "A": "心",
      "B": "肝",
      "C": "脾",
      "D": "腎"
    },
    "answer": "D",
    "category": "內經"
  },
  {
    "question": "中醫基礎理論中，關於血的敘述，下列何者錯誤？",
    "options": {
      "A": "主要由營氣和津液所組成，來源於脾胃對飲食物的運化而生成的水穀精微",
      "B": "下焦受氣，取汁，變化成赤，是謂血",
      "C": "精血互生轉化，精藏於腎，血藏於肝",
      "D": "肝藏血的功能，有防止出血的作用；脾除化生血液之外，還有統攝血液，使其行於脈中而不外溢"
    },
    "answer": "B",
    "category": "中醫基礎理論"
  },
  {
    "question": "金元四大家李杲依照當時人民的疾病，提出內傷學說，他描述有一種疾病主要因為「受勞役之疾，飲食又復失節，耽病日久」而得病。依《素問．太陰陽明論》所言，這類疾病與下列何者敘述最不符合？",
    "options": {
      "A": "陽明受傷，所以可能會出現身熱、無法安臥睡眠",
      "B": "這類疾病多為五臟疾病",
      "C": "若是影響四肢，可能會使得肌肉消瘦、四肢無力",
      "D": "如果此類疾病時間久，容易出現腹脹、腹瀉的症狀"
    },
    "answer": "A",
    "category": "中醫醫學史"
  },
  {
    "question": "躁鬱症患者在躁期會產生極度愉悅的情緒，表現出自我膨脹、精力旺盛、多話、性慾增加、睡眠時間縮短，並且會產生自制力降低和危機感降低的情形。依《靈樞．海論》的描述，與下列何者最為相關？",
    "options": {
      "A": "氣海有餘",
      "B": "血海有餘",
      "C": "水穀之海有餘",
      "D": "髓海有餘"
    },
    "answer": "D",
    "category": "內經"
  },
  {
    "question": "依《靈樞．天年》對生命不同階段的特點之描述，人生幾歲開始出現「腠理始疏，榮華頹落，髮頗斑白」？",
    "options": {
      "A": "40",
      "B": "50",
      "C": "60",
      "D": "70"
    },
    "answer": "A",
    "category": "內經"
  },
  {
    "question": "依照《素問．太陰陽明論》中有關脾、胃與津液之關係，下列敘述何者錯誤？",
    "options": {
      "A": "四肢不用是因水穀氣不得稟",
      "B": "脾為胃運行津液於太、少、厥陰經",
      "C": "胃主氣運行於六腑",
      "D": "邪氣侵入六腑則造成腹滿、腹瀉等症，久則為腸癖"
    },
    "answer": "D",
    "category": "內經"
  },
  {
    "question": "球隊教練為使球隊獲勝，根據不同情況，反覆斟酌策略，隨時進行調整與改變。依《靈樞．本神》篇之內容，此過程稱為下列何者？",
    "options": {
      "A": "意",
      "B": "志",
      "C": "思",
      "D": "智"
    },
    "answer": "C",
    "category": "內經"
  },
  {
    "question": "常人飲食進入體內的過程，依《難經．四十四難》七衝門之說，下列順序何者正確？",
    "options": {
      "A": "飛門、戶門、吸門、賁門",
      "B": "吸門、飛門、戶門、賁門",
      "C": "戶門、吸門、飛門、賁門",
      "D": "飛門、吸門、戶門、賁門"
    },
    "answer": "A",
    "category": "難經"
  },
  {
    "question": "依中醫基礎理論，衛氣的生理功能，下列何者錯誤？",
    "options": {
      "A": "護衛肌表，防禦外邪入侵",
      "B": "溫養臟腑、肌肉、皮毛",
      "C": "調控腠理的開闔，汗液的排泄",
      "D": "晝行於陰，夜行於陽"
    },
    "answer": "D",
    "category": "中醫基礎理論"
  },
   {
    "question": "依《靈樞．決氣》敘述，壅遏營氣，令無所避，是謂何者？",
    "options": {
      "A": "衛氣",
      "B": "脾",
      "C": "脈",
      "D": "心"
    },
    "answer": "C",
    "category": "內經"
  },
  {
    "question": "據《難經》所論，何者男子以藏精，女子以繫胞？",
    "options": {
      "A": "下焦",
      "B": "任脈",
      "C": "命門",
      "D": "血海"
    },
    "answer": "C",
    "category": "難經"
  },
  {
    "question": "下列有關「氣陷」病機的敘述，何者錯誤？",
    "options": {
      "A": "以氣的升舉無力為主要特徵",
      "B": "氣陷多由氣逆發展而來",
      "C": "可導致子宮下垂、脫肛",
      "D": "清陽不升易導致氣陷"
    },
    "answer": "B",
    "category": "中醫基礎理論"
  },
  {
    "question": "依《素問．靈蘭秘典論》，下列何者為「中正之官，決斷出焉」？",
    "options": {
      "A": "肝",
      "B": "膽",
      "C": "肺",
      "D": "心"
    },
    "answer": "B",
    "category": "內經"
  },
  {
    "question": "在五臟中，下列何者與女子胞的功能行使最有關係？",
    "options": {
      "A": "心、肝、肺、腎",
      "B": "心、肝、脾、肺",
      "C": "心、肝、脾、腎",
      "D": "脾、肝、肺、腎"
    },
    "answer": "C",
    "category": "內經"
  },
  {
    "question": "缺盆在經脈循行上常見有「缺盆中（腫）痛」的現象，依據《靈樞．經脈》，下面哪些經脈的是動所生病有缺盆中痛的相關描述？",
    "options": {
      "A": "手厥陰心包經，手太陰肺經",
      "B": "足太陽膀胱經，足少陽膽經",
      "C": "足陽明胃經，手厥陰心包經",
      "D": "手太陰肺經，足少陽膽經"
    },
    "answer": "D",
    "category": "內經"
  },
  {
    "question": "經脈的是動所生病常能直接提供疾病的病位，依據《靈樞．經脈》的內容，經脈是動所生病中依次提及「顏黑」、「面微有塵」、「面塵脫色」，下列何者正確？",
    "options": {
      "A": "足陽明胃經、足少陽膽經、足厥陰肝經",
      "B": "足少陰腎經、手太陽小腸經、足太陽膀胱經",
      "C": "足太陽膀胱經、足少陰腎經、足厥陰肝經",
      "D": "足少陽膽經、足少陰腎經、足太陰脾經"
    },
    "answer": "A",
    "category": "內經"
  },
  {
    "question": "依《靈樞．經脈》所述，胃足陽明之脈的脈盛和脈虛之人迎和寸口的比較，下列何者正確？",
    "options": {
      "A": "盛者，人迎大三倍於寸口；虛者，人迎反小於寸口也",
      "B": "盛者，寸口大三倍於人迎；虛者，寸口反小於人迎也",
      "C": "盛者，人迎大再倍於寸口；虛者，人迎反小於寸口也",
      "D": "盛者，寸口大再倍於人迎；虛者，寸口反小於人迎也"
    },
    "answer": "A",
    "category": "內經"
  },
  {
    "question": "在判別各經脈疾病的虛實，氣絕與否，主要是在觀察部位，下列敘述何者正確？",
    "options": {
      "A": "腎足少陰脈的氣絕是肉緊束，落髮多，骨肉相親",
      "B": "肺手太陰脈的氣絕則是看皮毛的狀態，皮毛焦，爪枯毛折",
      "C": "脾足太陰脈的氣絕則是肌肉硬，舌萎偏，唇反者",
      "D": "心手少陰脈的氣絕則是血瘀青，脈不榮肌，絕汗出"
    },
    "answer": "B",
    "category": "內經"
  },
  {
    "question": "李小姐皮膚長贅疣，小的如指頭大乾結作癢的痂疥，脈診人迎反小於寸口，依《靈樞．經脈》所述，應選下列何穴位最適宜？",
    "options": {
      "A": "偏歷",
      "B": "外關",
      "C": "飛揚",
      "D": "支正"
    },
    "answer": "D",
    "category": "內經"
  },
    {
    "question": "依據《難經》，關於五臟六腑原穴之敘述，下列何者錯誤？",
    "options": {
      "A": "肺之原，出於太淵",
      "B": "膀胱之原，出於束谷",
      "C": "大腸之原，出於合谷",
      "D": "心之原，出於神門"
    },
    "answer": "B",
    "category": "難經"
  },
  {
    "question": "依據《靈樞．經筋》的敘述，與手心主之筋並行者為何經筋？",
    "options": {
      "A": "手太陰之筋",
      "B": "手太陽之筋",
      "C": "手少陰之筋",
      "D": "手少陽之筋"
    },
    "answer": "A",
    "category": "內經"
  },
  {
    "question": "依《難經．七十九難》子母迎隨法，欲取足太陽膀胱經上之子穴行瀉法，最適當之穴位為？",
    "options": {
      "A": "至陰",
      "B": "束骨",
      "C": "崑崙",
      "D": "委中"
    },
    "answer": "B",
    "category": "難經"
  },
  {
    "question": "依《靈樞．衛氣》中，「氣街所治者，頭痛眩仆，腹痛中滿暴脹，及有新積」。取此者，應用下列九針中何者最適宜？",
    "options": {
      "A": "毫鍼",
      "B": "圓鍼",
      "C": "鍉鍼",
      "D": "長鍼"
    },
    "answer": "A",
    "category": "內經"
  },
  {
    "question": "依《靈樞．經脈》關於足少陽膽經是動病與所生病之敘述，下列何者錯誤？",
    "options": {
      "A": "是主骨所生病者",
      "B": "頷痛，目銳眥痛，缺盆中腫痛，腋下腫，馬刀俠癭",
      "C": "汗出發熱，瘧",
      "D": "胸、脅、肋、髀、膝外至脛、絕骨、外踝前及諸節皆痛，小趾次趾不用"
    },
    "answer": "C",
    "category": "內經"
  },
  {
    "question": "依《靈樞．經筋》，足少陽之筋，其病小指次指支轉筋，引膝外轉筋，膝不可屈伸，膕筋急，前引髀，後引尻，……，若傷左角，則應為下列何者？",
    "options": {
      "A": "右足不用",
      "B": "左足不用",
      "C": "右手不用",
      "D": "左手不用"
    },
    "answer": "A",
    "category": "內經"
  },
  {
    "question": "王先生因為最近顏面神經拘攣的症狀，臨床醫師幫他針刺足陽明胃經的下關穴後，突然感覺脅肋部位有悶脹的感覺。從經脈交會的角度來評估，這種悶脹感最可能隸屬下列那一條經絡？",
    "options": {
      "A": "手少陰心經",
      "B": "足陽明胃經",
      "C": "足厥陰肝經",
      "D": "足少陽膽經"
    },
    "answer": "D",
    "category": "內經"
  },
  {
    "question": "依《難經》，有關五臟六腑井滎俞經合之敘述，下列何者錯誤？",
    "options": {
      "A": "陰俞土，陽俞木",
      "B": "五臟六腑之有病者，皆取其原也",
      "C": "夏刺滎者，邪在心，季夏刺俞者，邪在脾",
      "D": "所出為井，所行為滎，所注為俞，所流為經，所入為合"
    },
    "answer": "D",
    "category": "難經"
  },
  {
    "question": "《靈樞．衛氣》中談到了十二經之標本部位。有關六陰經的標本內容，下列何者正確？",
    "options": {
      "A": "手厥陰之本在寸口之中",
      "B": "手太陰之本在銳骨之端",
      "C": "足少陰之標在內踝上三寸",
      "D": "足厥陰之標在背俞"
    },
    "answer": "D",
    "category": "內經"
  },
  {
    "question": "依《難經．二十六難》所記載，別絡有十五，其中包含十二正經之別絡，其餘三別絡不包含下列何者？",
    "options": {
      "A": "陰絡",
      "B": "衝脈之別",
      "C": "陽絡",
      "D": "脾之大絡"
    },
    "answer": "B",
    "category": "難經"
  },
  {
    "question": "依據《靈樞．順氣一日分為四時》的觀點，因時序不同而取穴的原則，下列何者錯誤？",
    "options": {
      "A": "春刺滎",
      "B": "夏刺俞",
      "C": "秋刺經",
      "D": "冬刺井"
    },
    "answer": "C",
    "category": "內經"
  },
  {
    "question": "一男子兩側鬢髮開始出現白髮，面部易憔悴較無光澤。依《素問．上古天真論》推估此男子年紀大約是？",
    "options": {
      "A": "四十歲",
      "B": "四十八歲",
      "C": "五十六歲",
      "D": "六十四歲"
    },
    "answer": "B",
    "category": "內經"
  },
  {
    "question": "依《素問．異法方宜論》的描述，地理環境因為其特殊環境造就的體質差異，下列何者正確？",
    "options": {
      "A": "東方因處海邊，飲食多吃魚而嗜鹹，因鹹傷腎，體質容易產生水腫疾病",
      "B": "西方因多為砂石之地，氣候乾燥，風大，肌膚腠理大多強健不易受外邪侵襲，故多為飲食內傷疾病",
      "C": "北方因地勢高，天氣寒冷，居民喜吃溫熱食物與酒，故容易產生發熱、生瘡的疾病",
      "D": "南方因地勢低下，陽熱盛而水濕聚集，故容易造成食慾不振、腹泄"
    },
    "answer": "B",
    "category": "內經"
  },
  {
    "question": "65歲男性在與客戶應酬後走出室外，突然心胸憋悶感，出現大汗、紫紺、肢冷發青等現象。以上症狀最符合《內經》、《難經》中之何病名？",
    "options": {
      "A": "心痹",
      "B": "肺痹",
      "C": "厥心痛",
      "D": "真心痛"
    },
    "answer": "D",
    "category": "難經"
  },
  {
    "question": "《難經．四十九難》論述五邪所傷之別，並以心病為例，則下列敘述何者錯誤？",
    "options": {
      "A": "中風得之，其色當赤",
      "B": "傷寒得之，當譫言妄語",
      "C": "傷暑得之，當喜汗出不可止",
      "D": "飲食勞倦得之，當喜苦味也"
    },
    "answer": "C",
    "category": "難經"
  },
  {
    "question": "《難經．六十難》論述頭心之痛，有厥痛，有真痛，下列敘述何者錯誤？",
    "options": {
      "A": "手三陽之脈，受風寒，伏留不去者，名厥頭痛",
      "B": "入連在腦者，名真頭痛",
      "C": "真心痛者，旦發夕死，夕發旦死",
      "D": "五臟中風寒者，名厥心痛"
    },
    "answer": "D",
    "category": "難經"
  },
  {
    "question": "依《素問．舉痛論》論述百病生於氣也，下列敘述何者正確？",
    "options": {
      "A": "怒則氣亂",
      "B": "喜則氣上",
      "C": "悲則氣泄",
      "D": "思則氣結"
    },
    "answer": "D",
    "category": "內經"
  },
  {
    "question": "關於中醫病因學的發展，下列何者錯誤？",
    "options": {
      "A": "《左傳》記載春秋時代醫和最早提出引起疾病的六氣，為風寒暑濕燥火",
      "B": "《素問．調經論》說夫邪之生也，或生於陰，或生於陽",
      "C": "《金匱要略》記載千般疢難，不越三條，將病因分成三類",
      "D": "《三因極一病證方論》提出六淫為外所因，七情為內所因，以及不內外因"
    },
    "answer": "A",
    "category": "內經"
  },
  {
    "question": "依《素問．痿論》關於五藏使人痿之論述，下列敘述何者錯誤？",
    "options": {
      "A": "肺熱葉焦，則皮毛虛弱急薄，著則生皮痿也",
      "B": "脾氣熱，則胃乾而渴，肌肉不仁，發為肉痿",
      "C": "肝氣熱，則膽泄口苦筋膜乾，筋膜乾則筋急而攣，發為筋痿",
      "D": "腎氣熱，則腰脊不舉，骨枯而髓減，發為骨痿"
    },
    "answer": "A",
    "category": "內經"
  },
  {
    "question": "依《素問．調經論》論述神、氣、血、形、志等的病症，下列敘述何者正確？",
    "options": {
      "A": "形：血氣未并，五藏安定，邪客於形，洒淅起於毫毛，未入於經絡",
      "B": "氣：血氣未并，五藏安定，皮膚微病",
      "C": "志：血氣未并，五藏安定，肌肉蠕動",
      "D": "神：血氣未并，五藏安定，骨節有動"
    },
    "answer": "B",
    "category": "內經"
  },
  {
    "question": "依《素問．調經論》論述內外寒熱的機理，下列敘述何者正確？",
    "options": {
      "A": "陽受氣於上焦，寒氣在外，則上焦不通，上焦不通，則寒氣獨留於外，此為陰虛則外寒",
      "B": "厥氣上逆，寒氣積於胸中而不瀉，不瀉則溫氣去，寒獨留，則血凝泣，凝則脈不通，此為陰盛則內寒",
      "C": "有所勞倦，形氣衰少，穀氣不盛，上焦不行，下脘不通，胃氣熱，熱氣熏胸中，此為陽盛則內熱",
      "D": "上焦不通利，則皮膚緻密，腠理閉塞，玄府不通，衛氣不得泄越，此為陽虛則外熱"
    },
    "answer": "B",
    "category": "內經"
  },
  {
    "question": "依《素問．至真要大論》論述病機分析，下列敘述何者錯誤？",
    "options": {
      "A": "諸痛癢瘡，皆屬於肺",
      "B": "諸寒收引，皆屬於腎",
      "C": "諸風掉眩，皆屬於肝",
      "D": "諸濕腫滿，皆屬於脾"
    },
    "answer": "A",
    "category": "內經"
  },
  {
    "question": "依《素問．風論》所述風邪入侵的病機次序，身體出現「畏寒」的機制為下列何者？",
    "options": {
      "A": "脾胃虛弱",
      "B": "肺氣不足",
      "C": "腠理開",
      "D": "腠理閉"
    },
    "answer": "C",
    "category": "內經"
  },
  {
    "question": "依《靈樞．順氣一日分為四時》，有關一天裡面人體疾病進退之敘述，下列何者正確？",
    "options": {
      "A": "朝則人氣長，長則勝邪，故旦慧",
      "B": "日中人氣始衰，邪氣始生，故安",
      "C": "夕則人氣始生，病氣衰，故加",
      "D": "夜半人氣入臟，邪氣獨居於身，故甚"
    },
    "answer": "D",
    "category": "內經"
  },
  {
    "question": "依據中醫基本理論，寒邪的性質和致病特點，下列何者最正確？",
    "options": {
      "A": "為陰邪，其性下行",
      "B": "其性重濁，可致周身酸痛",
      "C": "先傷肺，出現咳嗽痰少症狀",
      "D": "其性凝滯，引起疼痛"
    },
    "answer": "D",
    "category": "內經"
  },
  {
    "question": "《難經．十四難》有關「根脈」部位的論述，下列何者最適宜？",
    "options": {
      "A": "寸部",
      "B": "人迎",
      "C": "尺部",
      "D": "趺陽"
    },
    "answer": "C",
    "category": "難經"
  },
  {
    "question": "根據《難經．十六難》有關脾脈內外證的論述，下列何者最不適宜？",
    "options": {
      "A": "善噫善味",
      "B": "體重節痛",
      "C": "腹脹食消",
      "D": "當臍有動氣"
    },
    "answer": "C",
    "category": "難經"
  },
  {
    "question": "40歲男性，連續發高燒至40℃已2日，腹脹滿，沒胃口不想吃東西，神志不清，胡言亂語。依《素問．熱論》論述而言，有關其可能之致病病機，下列何者正確？",
    "options": {
      "A": "此乃兩感於熱，預後佳",
      "B": "此乃兩感於溫，當用汗法",
      "C": "此乃兩感於寒，預後差",
      "D": "此乃兩感於燥，當用潤法"
    },
    "answer": "C",
    "category": "內經"
  },
  {
    "question": "依《難經．五十八難》中有關外感脈象之敘述，下列何者正確？",
    "options": {
      "A": "溫病之脈，陽浮而弱，陰小而急",
      "B": "中風之脈，陽浮而滑，陰濡而弱",
      "C": "濕溫之脈，陰陽俱浮，浮之而滑",
      "D": "熱病之脈，陽浮而盛，陰大而散"
    },
    "answer": "B",
    "category": "難經"
  },
  {
    "question": "《素問．生氣通天論》中關於煎厥的敘述，下列何者正確？",
    "options": {
      "A": "大怒則形氣絕，而血菀於上",
      "B": "煩勞則張，精絕，辟積于夏",
      "C": "陽氣衰于下",
      "D": "陰氣衰于下"
    },
    "answer": "B",
    "category": "內經"
  },
   {
    "question": "依據《素問．風論》、《素問．病能論》中關於風證之敘述，下列何者錯誤？",
    "options": {
      "A": "酒風，病身熱解墮，汗出如浴，惡風少氣",
      "B": "酒風，治以澤瀉、朮各十分，糜銜五分，合以三指撮為後飯",
      "C": "飲酒中風，則為漏風",
      "D": "外在腠理，則為脾風"
    },
    "answer": "D",
    "category": "內經"
  },
  {
    "question": "依據《素問．生氣通天論》有關四時之氣更傷五臟之敘述，下列何者錯誤？",
    "options": {
      "A": "春傷於風，乃為洞泄",
      "B": "夏傷於暑，秋為痎瘧",
      "C": "秋傷於燥，發為痿厥",
      "D": "冬傷於寒，春必溫病"
    },
    "answer": "C",
    "category": "內經"
  },
  {
    "question": "依據《難經．三十七難》中提到「關格」之論述，下列何者錯誤？",
    "options": {
      "A": "邪在經絡，導致陰陽脈盛相斥，不得相營",
      "B": "關格是陰陽氣盛的危候",
      "C": "陽氣太盛，則陰氣不得相營也，曰關",
      "D": "陰氣太盛，則陽氣不得相營也，曰格"
    },
    "answer": "A",
    "category": "難經"
  },
  {
    "question": "患者數日以來，出現神疲乏力，頭暈目眩，腹脹，泄瀉等症狀。從清氣、濁氣來考量，此病證下列何者最正確？",
    "options": {
      "A": "胃氣不降，濁氣在上",
      "B": "脾虛不升，清氣在下",
      "C": "脾虛不升，濁氣在上",
      "D": "胃氣下降，清氣在下"
    },
    "answer": "B",
    "category": "內經"
  },
  {
    "question": "20歲女大學生因失戀而失眠前來就診，給與針灸及藥物治療後仍療效不佳，下列敘述何者較正確？",
    "options": {
      "A": "壯火食氣，精氣弛壞，魂魄歸之而病不愈",
      "B": "因哀悲動中者，神憚散而不藏，神散之故病不可愈",
      "C": "愁憂者，則神蕩而不收，神迷惑而病不愈",
      "D": "精神不進，志意不治，故病不可愈"
    },
    "answer": "D",
    "category": "內經"
  },
  {
    "question": "依《素問．欬論》，若病人咳嗽日久，產生咳而失氣，氣與咳俱失，則選擇下列何穴治療最適宜？",
    "options": {
      "A": "足三里",
      "B": "委中",
      "C": "天井",
      "D": "小海"
    },
    "answer": "D",
    "category": "內經"
  },
  {
    "question": "依《靈樞．癰疽》，有關「疽」之病機病證敘述，下列何者錯誤？",
    "options": {
      "A": "皮夭以堅",
      "B": "下陷肌膚",
      "C": "內連六腑",
      "D": "血氣竭"
    },
    "answer": "C",
    "category": "內經"
  },
  {
    "question": "依《靈樞．五禁》，有關五逆之敘述，下列何者正確？",
    "options": {
      "A": "熱病脈靜，汗未出，脈盛躁",
      "B": "病泄，脈細無力",
      "C": "著痹不移，䐃肉破，身熱，脈偏絕",
      "D": "寒熱奪形，脈細弱"
    },
    "answer": "C",
    "category": "內經"
  },
  {
    "question": "患者外感寒邪，頭項強痛，體溫達攝氏39℃，其脈浮緊。依據《素問．至真要大論》，傷寒得太陽病而發熱，太陽之氣有下列何種特性？",
    "options": {
      "A": "寒為本，太陽為標，太陽從本從標",
      "B": "寒為本，太陽為標，太陽不從本從標",
      "C": "寒為標，太陽為本，太陽從本從標",
      "D": "寒為標，太陽為本，太陽不從本從標"
    },
    "answer": "A",
    "category": "內經"
  },
  {
    "question": "依《素問．病能》，有關頸癰的患者之治療方式，下列敘述何者正確？",
    "options": {
      "A": "氣虛氣血不行之患者，易患頸癰",
      "B": "不可切開排膿，以免內陷",
      "C": "夫氣盛血聚者，不宜石而瀉之，需以內服藥治療",
      "D": "癰氣之息者，宜以鍼開除去之"
    },
    "answer": "D",
    "category": "內經"
  },
  {
    "question": "關於陶弘景之敘述，下列何者錯誤？",
    "options": {
      "A": "陶弘景，南北朝時期著名醫學家、道家",
      "B": "《本草經集注》載藥 730 種，是陶弘景由《名醫別錄》與《神農本草經》中選錄整理補充出來的",
      "C": "陶弘景編撰《本草經集注》時採用朱墨分書的方法明確新舊資料內容",
      "D": "陶弘景《本草經集注》原書於明代《本草綱目》問世後逐漸亡佚"
    },
    "answer": "D",
    "category": "中醫醫學史"
  },
  {
    "question": "下列何者為漢代的名醫？",
    "options": {
      "A": "長桑君",
      "B": "太倉公",
      "C": "扁鵲",
      "D": "醫和"
    },
    "answer": "B",
    "category": "中醫醫學史"
  },
  {
    "question": "隋唐時期有大量中外醫學交流，《外臺祕要》中「四大說」最可能來自哪國？",
    "options": {
      "A": "韓國",
      "B": "印度",
      "C": "越南",
      "D": "阿拉伯"
    },
    "answer": "B",
    "category": "中醫醫學史"
  },
  {
    "question": "下列何者非為唐代太醫署醫學教育的分科之一？",
    "options": {
      "A": "醫科",
      "B": "針科",
      "C": "婦人科",
      "D": "咒禁科"
    },
    "answer": "C",
    "category": "中醫醫學史"
  },
  {
    "question": "《神農本草經》的內容論述與相關資料，是引自下列何書及文體？",
    "options": {
      "A": "《大觀本草》；朱文（陽刻）",
      "B": "《大觀本草》；白文（陰刻）",
      "C": "《證類本草》；朱文（陽刻）",
      "D": "《證類本草》；白文（陰刻）"
    },
    "answer": "D",
    "category": "中醫醫學史"
  },
  {
    "question": "關於金元四大家理論，下列何者正確？",
    "options": {
      "A": "劉完素的「火熱論」主要認為六氣挾內傷七情而化火",
      "B": "朱丹溪的「相火論」認為「引火歸原」是處理相火妄動的方法",
      "C": "李東垣認為補脾胃需從上、中、下三焦元氣來補才算完備，也必須重視補養「胃陰」",
      "D": "張從正認為能增益五臟均可謂補，能促使病人進食則是真補之道"
    },
    "answer": "D",
    "category": "中醫醫學史"
  },
  {
    "question": "中醫癘氣論倡導避癘，《瘟疫論》由誰撰寫？",
    "options": {
      "A": "吳有性；十七世紀上半葉",
      "B": "陳司成；十七世紀上半葉",
      "C": "吳有性；十七世紀下半葉",
      "D": "陳司成；十七世紀下半葉"
    },
    "answer": "A",
    "category": "中醫醫學史"
  },
  {
    "question": "下列關於「溫病四大家」配對，何者錯誤？",
    "options": {
      "A": "吳鞠通－《醫醫病書》",
      "B": "葉天士－《疫疹窮源》",
      "C": "王孟英－《四科簡效方》",
      "D": "薛生白－《醫經原旨》"
    },
    "answer": "B",
    "category": "中醫醫學史"
  },
  {
    "question": "老官山漢墓醫簡內容與《漢書．藝文志》方技略中的哪派有關？",
    "options": {
      "A": "扁鵲",
      "B": "基督",
      "C": "甄權",
      "D": "佛陀"
    },
    "answer": "A",
    "category": "中醫醫學史"
  },
  {
    "question": "下列何者著有《釐正按摩要術》，並介紹小兒「胸腹按診法」？",
    "options": {
      "A": "周松齡",
      "B": "張振鋆",
      "C": "葉隱衡",
      "D": "朱風穉"
    },
    "answer": "B",
    "category": "中醫醫學史"
  },
  {
    "question": "依《素問．陰陽應象大論》六氣偏勝的病理機轉，下列何者錯誤？",
    "options": {
      "A": "風勝則動",
      "B": "熱勝則腫",
      "C": "寒勝則乾",
      "D": "濕勝則濡瀉"
    },
    "answer": "C",
    "category": "內經"
  },
  {
    "question": "豬肉雖然為生活中常見的食品，但從中醫角度來看仍然有其特性。依《素問．金匱真言論》中的描述，豬肉與下列何者的特性符合？",
    "options": {
      "A": "五行屬金",
      "B": "氣味臊臭",
      "C": "四時對應太白星",
      "D": "味鹹入腎"
    },
    "answer": "D",
    "category": "中醫基礎理論"
  },
  {
    "question": "《鍼灸聚英》內提出「四總穴」為「肚腹三里留，腰背委中求；頭項尋列缺，面口合谷收」。依《素問．陰陽離合論》的內容，循行至頭項部的膀胱經與列缺穴所在的肺經有何共同關係？",
    "options": {
      "A": "太陽為開，太陰為開",
      "B": "陽明為闔，少陰為闔",
      "C": "少陽為樞，厥陰為樞",
      "D": "少陽為樞，少陰為樞"
    },
    "answer": "A",
    "category": "中醫基礎理論"
  },
  {
    "question": "《景岳全書．新方八陣．補略》：「善補陽者，必於陰中求陽，則陽得陰助而生化無窮；善補陰者，必於陽中求陰則陰得陽生，而泉源不竭」，這段話之意義與下列《黃帝內經》內容何者最相近？",
    "options": {
      "A": "陰陽者，血氣之男女也；左右者，陰陽之道路也；水火者，陰陽之徵兆也",
      "B": "陰在內，陽之守也；陽在外，陰之使也",
      "C": "陰陽者，天地之道也",
      "D": "陰陽者，數之可十，推之可百，數之可千，推之可萬"
    },
    "answer": "B",
    "category": "中醫基礎理論"
  },
  {
    "question": "依《素問．金匱真言論》所記載，有關陰陽以一天晝夜的敘述，下列何者為陽中之陰？",
    "options": {
      "A": "平旦至日中",
      "B": "日中至黃昏",
      "C": "合夜至雞鳴",
      "D": "雞鳴至平旦"
    },
    "answer": "B",
    "category": "中醫基礎理論"
  },
  {
    "question": "法於陰陽的具體方法，體現在《素問．四氣調神大論》，下列敘述何者正確？",
    "options": {
      "A": "春夏養陰，秋冬養陽",
      "B": "春夏養陽，秋冬養陰",
      "C": "夏三月，養生之道",
      "D": "冬三月，養收之道"
    },
    "answer": "B",
    "category": "中醫基礎理論"
  },
  {
    "question": "生活起居情況過度，易會損傷人體健康，依《素問．宣明五氣論》的論述，下列何者正確？",
    "options": {
      "A": "久行傷骨",
      "B": "久立傷筋",
      "C": "久臥傷氣",
      "D": "久坐傷血"
    },
    "answer": "C",
    "category": "中醫基礎理論"
  },
  {
    "question": "5歲幼童溜滑梯時不慎跌倒，導致右小腿腫脹，回家後患處逐漸發熱疼痛而嚎啕大哭，依《素問．陰陽應象大論》中陰陽形氣之敘述，下列何者最適宜？",
    "options": {
      "A": "此為熱傷形也",
      "B": "此為氣傷腫也",
      "C": "形氣受傷會相互影響是因陰陽對立的緣故",
      "D": "此為形傷氣也"
    },
    "answer": "D",
    "category": "中醫基礎理論"
  },
  {
    "question": "若於春天不能順時而養其生發之氣，到了夏天會因奉長者少而產生下列何種情形？",
    "options": {
      "A": "痎瘧",
      "B": "寒變",
      "C": "痿厥",
      "D": "飱泄"
    },
    "answer": "B",
    "category": "中醫基礎理論"
  },
  {
    "question": "依《素問．四氣調神大論》，四季的陰陽是萬物終始（死生）之本，而其中的夏季對應大自然消長規律中的何階段？",
    "options": {
      "A": "長",
      "B": "收",
      "C": "藏",
      "D": "生"
    },
    "answer": "A",
    "category": "中醫基礎理論"
  },
  {
    "question": "《靈樞．本神》篇中關於精神疾病造成的五臟病變，下列敘述何者錯誤？",
    "options": {
      "A": "怵惕思慮則傷神，神傷則恐懼自失，屬傷心",
      "B": "陰縮而攣筋，兩脅骨不舉，毛悴色夭死於秋，屬傷肝",
      "C": "悲哀動中則傷魂，魂傷則狂忘不精，不精則不正，屬傷肝",
      "D": "恐懼而不解則傷神，神傷則骨酸痿厥，精時自下"
    },
    "answer": "D",
    "category": "中醫基礎理論"
  },
  {
    "question": "患有高血壓及胃潰瘍疾病多年病患。近日行走跌倒後診為「肌少症」，握力肌力測試只有 18 kg（正常應大於 26 kg），行走速度並未變慢，偶爾覺得提重物時比較沒有力氣，生活起居未感受到任何影響。依據《素問．五臟生成》敘述，病患病證與下列何臟腑最無關？",
    "options": {
      "A": "脾",
      "B": "心",
      "C": "肺",
      "D": "肝"
    },
    "answer": "C",
    "category": "中醫基礎理論"
  },
  {
    "question": "依據《素問．六節臟象論》之內容，「肝者，罷極之本」。下列關於肝的敘述何者錯誤？",
    "options": {
      "A": "魂之居也",
      "B": "其華在爪",
      "C": "其充在筋",
      "D": "精之處也"
    },
    "answer": "D",
    "category": "中醫基礎理論"
  },
  {
    "question": "依《靈樞．決氣》所述，人有六氣。關於「骨屬屈伸不利，色夭，腦髓消，脛痠，耳數鳴」，最可能為六氣之中何者耗竭的臨床表現？",
    "options": {
      "A": "血脫",
      "B": "精脫",
      "C": "津脫",
      "D": "液脫"
    },
    "answer": "D",
    "category": "中醫基礎理論"
  },
  {
    "question": "一個人出現說夢話、夢遊，甚至出現幻覺、幻聽等症狀，依《難經》五臟藏七神之理論，此問題可歸因下列何臟腑？",
    "options": {
      "A": "肝",
      "B": "脾",
      "C": "肺",
      "D": "腎"
    },
    "answer": "A",
    "category": "中醫基礎理論"
  },
  {
    "question": "依《難經．三十五難》，下列關於六腑之敘述，何者錯誤？",
    "options": {
      "A": "小腸者，受盛之府",
      "B": "大腸者，傳瀉行道之府",
      "C": "膽者，清淨之府",
      "D": "三焦者，津液之府"
    },
    "answer": "D",
    "category": "中醫基礎理論"
  },
  {
    "question": "人體之氣的主要來源包括下列何者？①先天之精氣 ②臟腑之氣 ③自然界之清氣 ④水穀之精氣 ⑤宗氣",
    "options": {
      "A": "②③④",
      "B": "①②⑤",
      "C": "①③④",
      "D": "②③⑤"
    },
    "answer": "C",
    "category": "中醫基礎理論"
  },
  {
    "question": "營衛之氣運行中，營氣之運行路徑，下列何者正確？",
    "options": {
      "A": "晝行陽，夜行陰",
      "B": "依十二經脈之時序而行",
      "C": "依十五別絡之時序而行",
      "D": "晝行陰，夜行陽"
    },
    "answer": "B",
    "category": "中醫基礎理論"
  },
  {
    "question": "依《素問．生氣通天論》之內容，若平時喜好辛辣食物，往後可能出現下列何狀況？",
    "options": {
      "A": "肝氣以津，脾氣乃絕",
      "B": "大骨氣勞，短肌",
      "C": "心氣喘滿，色黑",
      "D": "筋脈沮弛，精神乃央"
    },
    "answer": "D",
    "category": "中醫基礎理論"
  },
  {
    "question": "承上題，依《素問．生氣通天論》因飲食的偏嗜而造成的症狀，是依據下列何原理推測？",
    "options": {
      "A": "相生",
      "B": "相剋",
      "C": "相乘",
      "D": "相伍"
    },
    "answer": "C",
    "category": "中醫基礎理論"
  },
  {
    "question": "津液的生成來源主要依賴下列那些臟腑的功能？",
    "options": {
      "A": "心包與三焦",
      "B": "肺與大腸",
      "C": "腎與膀胱",
      "D": "脾與胃"
    },
    "answer": "D",
    "category": "中醫基礎理論"
  },
  {
    "question": "有關引起血虛之病因，下列敘述何者錯誤？",
    "options": {
      "A": "月經量過多，新血不及補充所致",
      "B": "因飲食營養不足，血液生成不足",
      "C": "脾胃虛弱者，生化血液功能減退",
      "D": "常見於發熱病症急性期，津液耗損，致血液暗耗"
    },
    "answer": "D",
    "category": "中醫基礎理論"
  },
  {
    "question": "56歲男性主管，面試一位員工，發現其嘴唇暗黑甚。依據《素問．五臟生成論》，嘴唇與下列那一個臟腑最相關？",
    "options": {
      "A": "腎",
      "B": "心",
      "C": "脾",
      "D": "肺"
    },
    "answer": "C",
    "category": "中醫基礎理論"
  },
  {
    "question": "依據《醫碥．卷之一．雜症》，「上下升降之樞紐」，指下列那一個臟的功能？",
    "options": {
      "A": "心",
      "B": "脾",
      "C": "肺",
      "D": "腎"
    },
    "answer": "B",
    "category": "中醫基礎理論"
  },
  {
    "question": "依《素問．靈蘭秘典論》，「作強之官，伎巧出焉」是指下列那一個臟腑的功能？",
    "options": {
      "A": "肝",
      "B": "肺",
      "C": "脾",
      "D": "腎"
    },
    "answer": "D",
    "category": "中醫基礎理論"
  },
  {
    "question": "三陰三陽是中醫天人合一的表徵。陰陽之道，何補何瀉，九鍼之玄，要在終始。依《靈樞．根結》的敘述，下列何者正確？",
    "options": {
      "A": "少陽根於竅陰，結於顙大",
      "B": "少陰根於湧泉，結於太倉",
      "C": "厥陰根於隱白，結於玉英",
      "D": "太陽根於至陰，結於命門"
    },
    "answer": "D",
    "category": "中醫基礎理論"
  },
  {
    "question": "依《靈樞．經脈》，關於心經循行與相關病候，下列敘述何者最適宜？",
    "options": {
      "A": "是動病有喉嚨痛、下頦腫，頭難以轉側",
      "B": "所生病有眼睛發黃，脅肋疼痛，掌心熱痛",
      "C": "盛者，人迎大一倍於寸口",
      "D": "其循行入缺盆，布膻中，散絡心胞，下膈，循屬於心"
    },
    "answer": "B",
    "category": "中醫基礎理論"
  },
  {
    "question": "依據《靈樞．經脈篇》之內容，關於經脈脈象的敘述，下列何者符合「盛者，寸口大再倍於人迎；虛者，寸口反小於人迎也」？",
    "options": {
      "A": "③⑦",
      "B": "②⑥",
      "C": "①⑤",
      "D": "④⑧"
    },
    "answer": "D",
    "category": "中醫基礎理論"
  },
  {
    "question": "依《靈樞．經脈》對於經脈的論述，下列何經脈「主筋所生病者」？",
    "options": {
      "A": "足少陰腎經",
      "B": "足太陽膀胱經",
      "C": "手厥陰心包經",
      "D": "手陽明大腸經"
    },
    "answer": "B",
    "category": "中醫基礎理論"
  },
  {
    "question": "一病患就診時主訴為覺得飢餓不想吃東西，剛躺下就想站起來，眼目昏花不清，心中動盪不寧，猶如飢餓的感覺，容易感到恐懼而且心惕惕跳動像是有人要來抓他，此疾病臨床上與那條經脈的是動病病變最相關？",
    "options": {
      "A": "手厥陰心包經",
      "B": "足少陰腎經",
      "C": "手太陰心經",
      "D": "足太陰脾經"
    },
    "answer": "B",
    "category": "中醫基礎理論"
  },
   {
    "question": "依《靈樞．經脈》，十五別絡中有關手厥陰絡脈的病症，下列敘述何者最適宜？",
    "options": {
      "A": "實則心痛，虛則頭強煩心",
      "B": "實則支膈，虛則不能言",
      "C": "實則肘孿，虛則不收",
      "D": "實則癲狂，虛則足不收"
    },
    "answer": "A",
    "category": "難經"
  },
  {
    "question": "依《靈樞．經脈》，有關十五別絡穴位及相關論述，下列何者錯誤？",
    "options": {
      "A": "足少陰之別，名曰大鍾。其病氣逆則煩悶，實則閉癃，虛則腰痛",
      "B": "足太陰之別，名曰公孫。去本節之後一寸，別走陽明；其別者，入絡腸胃，厥氣上逆則霍亂，實則腸中切痛；虛則鼓脹",
      "C": "手心主之別，名曰通里。去腕一寸半，別而上行，循經入于心中，系舌本，屬目系。其實則支膈，虛則不能言",
      "D": "脾之大絡，名曰大包。出淵腋下三寸，布胸脅。實則身盡痛，虛則百節盡皆縱"
    },
    "answer": "C",
    "category": "難經"
  },
  {
    "question": "根據《難經．六十八難》所描述五俞穴的相關主治病症，下列敘述何者錯誤？",
    "options": {
      "A": "井主心下滿",
      "B": "滎主身熱",
      "C": "俞主體重節痛",
      "D": "合主喘咳寒熱"
    },
    "answer": "D",
    "category": "難經"
  },
  {
    "question": "依《難經．二十八難》奇經八脈有病，其受邪氣，畜則腫熱，下列何者治療最適宜？",
    "options": {
      "A": "毫針",
      "B": "員針",
      "C": "三稜針",
      "D": "鍉針"
    },
    "answer": "C",
    "category": "難經"
  },
  {
    "question": "陽維、陰維者，維絡于身。關於組成陽維脈穴位的經絡，與下列何者最不相關？",
    "options": {
      "A": "足太陽",
      "B": "足少陽",
      "C": "足陽明",
      "D": "手三陽"
    },
    "answer": "C",
    "category": "難經"
  },
  {
    "question": "若病患主訴為舌本強、食則嘔、胃脘痛、腹脹與善噫，臨床上屬於何經脈之病候？",
    "options": {
      "A": "胃足陽明之脈",
      "B": "膽足少陽之脈",
      "C": "脾足太陰之脈",
      "D": "肝足厥陰之脈"
    },
    "answer": "C",
    "category": "難經"
  },
  {
    "question": "依《難經》，有關原穴之敘述，下列何者錯誤？",
    "options": {
      "A": "胃之原出於足三里",
      "B": "大腸之原出於合谷",
      "C": "肝之原出於太衝",
      "D": "膽之原出於丘墟"
    },
    "answer": "A",
    "category": "難經"
  },
  {
    "question": "根據《難經．二十八難》督脈者，起於下極之俞，並於脊裡，上至何處？",
    "options": {
      "A": "風府",
      "B": "風市",
      "C": "風門",
      "D": "風池"
    },
    "answer": "A",
    "category": "難經"
  },
  {
    "question": "依《靈樞．經脈》，有關膀胱經循行與相關病候，下列何者錯誤？",
    "options": {
      "A": "起於目內眥，上額，交巔；其支者，從巔至耳上角",
      "B": "其直者，從巔入絡腦，別出下項，循肩髆外，挾脊，抵腰中，入循膂，絡腎，屬膀胱",
      "C": "其支者，從腰中下挾脊貫臀，入膕中；其支者，從髆內左右別下貫胛，挾脊內，過髀樞",
      "D": "是主筋所生病者，痔、瘧、狂、癲疾、頭顖項痛，目黃、淚出，鼽衄"
    },
    "answer": "B",
    "category": "難經"
  },
  {
    "question": "有關《靈樞．經脈》十五絡與《難經》絡有十五之敘述，下列何者錯誤？",
    "options": {
      "A": "《靈樞．經脈》所載之十五別絡為十二正經、任脈、督脈、脾之大絡",
      "B": "《難經》之十五別絡為十二正經、陽絡、陰絡、脾之大絡",
      "C": "《難經》之十五別絡包含陽蹻之絡與陰蹻之絡",
      "D": "《靈樞．經脈》脾之大絡，名曰虛里，此脈若羅絡之血者，皆取之脾之大絡"
    },
    "answer": "D",
    "category": "難經"
  },
  {
    "question": "依《靈樞．五味》對宗氣的敘述，其大氣之搏而不行者，積於胸中，命為何者？",
    "options": {
      "A": "玉堂",
      "B": "華蓋",
      "C": "天突",
      "D": "氣海"
    },
    "answer": "D",
    "category": "難經"
  },
  {
    "question": "依據《靈樞．經脈》中之內容，關於「洒洒振寒，善呻，數欠，顏黑，汗出，鼽衄，口喎，唇胗，頸腫，喉痹」，是屬於下列何經脈之是動或所生病？",
    "options": {
      "A": "肝",
      "B": "心",
      "C": "脾",
      "D": "胃"
    },
    "answer": "D",
    "category": "難經"
  },
  {
    "question": "42 歲林女士，最近常覺臍旁不舒，飽則大，飢則小。依《靈樞．百病始生》所述，下列病名何者正確？",
    "options": {
      "A": "孫絡之積",
      "B": "緩筋之積",
      "C": "膂筋之積",
      "D": "募元之積"
    },
    "answer": "B",
    "category": "難經"
  },
  {
    "question": "林小姐年方十八，體弱多病，今日就診發現：顴小皮薄肉弱，兩臂瘦弱無力，地閤色澤灰暗，與天庭色澤不一，依《靈樞．五變》所述，下列分析何者最適宜？",
    "options": {
      "A": "善病風厥",
      "B": "善病消癉",
      "C": "善病痺者",
      "D": "善病寒熱"
    },
    "answer": "D",
    "category": "難經"
  },
  {
    "question": "依據《素問．至真要大論》關於病機的描述，下列何者錯誤？",
    "options": {
      "A": "諸風掉眩，皆屬於肝",
      "B": "諸熱瞀瘛，皆屬於火",
      "C": "諸痙項強，皆屬於濕",
      "D": "諸禁鼓慄，如喪神守，皆屬於木"
    },
    "answer": "D",
    "category": "難經"
  },
  {
    "question": "根據《素問．玉機真藏論》中關於五臟疾病的傳變與預後，下列何者錯誤？",
    "options": {
      "A": "肝受氣於心，傳之於脾",
      "B": "五臟有病各傳其所勝",
      "C": "肝之病傳至肺而死",
      "D": "心之病傳至脾而死"
    },
    "answer": "D",
    "category": "內經"
  },
  {
    "question": "依《素問．五藏生成論》論述，「故人臥血歸於肝，……，指受血而能攝」。依此內容，臥出而風吹之，血凝於何處，分別會產生「痹」、「泣」、「厥」等症？",
    "options": {
      "A": "足、目、膚",
      "B": "膚、脈、足",
      "C": "指掌、目、足",
      "D": "膚、脈、指掌"
    },
    "answer": "B",
    "category": "內經"
  },
  {
    "question": "小明夏天常正午到戶外玩，大汗出後，喝冰水，洗冰冷水澡；秋天氣候轉涼，不慎受風邪，出現寒熱往來交替症狀。依《素問．瘧論》論述，小明的瘧病屬於何種？",
    "options": {
      "A": "溫瘧",
      "B": "癉瘧",
      "C": "暑瘧",
      "D": "寒瘧"
    },
    "answer": "D",
    "category": "內經"
  },
  {
    "question": "王執行長因生意往來奔波數國，突發眼睛視物不明、耳鳴，又加上天氣悶熱而中暑昏迷。依《素問．生氣通天論》的描述，此應為何種病症？",
    "options": {
      "A": "薄厥",
      "B": "煎厥",
      "C": "偏枯",
      "D": "痤疿"
    },
    "answer": "B",
    "category": "內經"
  },
  {
    "question": "麻黃湯常用於治療「頭痛，發熱，身疼，腰痛，骨節疼痛，惡風，無汗而喘」等症狀。依《靈樞．百病始生篇》的描述，這時候病邪最可能傳舍於何處？",
    "options": {
      "A": "皮膚",
      "B": "絡脈",
      "C": "經",
      "D": "輸"
    },
    "answer": "D",
    "category": "內經"
  },
    {
    "question": "依據《素問．生氣通天論》之內容，四時之氣更傷五臟，下列敘述何者正確？",
    "options": {
      "A": "春傷於風，夏生咳嗽",
      "B": "夏傷於暑，秋生咳瘧",
      "C": "秋傷於濕，冬生洞泄",
      "D": "冬傷於寒，春生痿厥"
    },
    "answer": "B",
    "category": "內經"
  },
  {
    "question": "依《素問．調經論》論述氣、血、形、志之有餘及不足的症狀，下列敘述何者正確？",
    "options": {
      "A": "氣有餘則笑不止，不足則悲",
      "B": "形有餘則腹脹飱泄，不足則厥",
      "C": "血有餘則怒，不足則恐",
      "D": "志有餘則腹脹、涇溲不利，不足則四支不用"
    },
    "answer": "C",
    "category": "內經"
  },
  {
    "question": "依《素問．臟氣法時論》論述不同病證的不同臟氣虛實，下列敘述何者正確？",
    "options": {
      "A": "腎病者：虛則目䀮䀮無所見，耳無所聞，善恐如人將捕之",
      "B": "心病者：虛則胸腹大，脇下與腰相引而痛",
      "C": "肝病者：虛則少氣不能報息，耳聾嗌乾",
      "D": "肺病者：虛則胸中痛，大腹小腹痛，清厥，意不樂"
    },
    "answer": "B",
    "category": "內經"
  },
  {
    "question": "一婦人晚上睡覺遇到小偷闖空門，自此之後夜晚便不安睡。依據《素問．舉痛論》之內容，其中的病機最符合下列何者？",
    "options": {
      "A": "熱則氣泄",
      "B": "驚則氣亂",
      "C": "恐則氣下",
      "D": "思則氣結"
    },
    "answer": "B",
    "category": "內經"
  },
  {
    "question": "承上題，其中之病機機轉為何？",
    "options": {
      "A": "上焦不通，榮衛不散",
      "B": "上焦閉，下焦脹，氣不行",
      "C": "心有所存，神有所歸",
      "D": "心無所倚，慮無所定"
    },
    "answer": "D",
    "category": "內經"
  },
  {
    "question": "依《素問．風論》有關「癘風」的論述，下列敘述何者最適宜？",
    "options": {
      "A": "風氣與太陰俱入",
      "B": "風氣與少陰俱入",
      "C": "風氣與陽明俱入",
      "D": "風氣與太陽俱入"
    },
    "answer": "D",
    "category": "內經"
  },
  {
    "question": "依《素問．熱論》論述，對於人之傷於寒，其所產生的症狀與病程表現，下列何者錯誤？",
    "options": {
      "A": "兩感於寒而病者，必不免於死",
      "B": "巨陽受之，頭項痛，腰脊強",
      "C": "陽明受之，身熱目疼而腹滿嗌乾",
      "D": "少陽受之，胸脇痛而耳聾"
    },
    "answer": "C",
    "category": "內經"
  },
  {
    "question": "35 歲男性發高燒至 39.5℃，咳嗽、畏寒，舌質紅，苔黃，脈數，經住院治療 3 天後燒已退，第 4 天出院時中午自覺要增強免疫力，點了一客牛排吃後，夜間又發燒到 38.5℃，頭痛、腹脹滿、嗝氣且咳嗽更甚。依《素問．熱論》有關其可能之致病病機，下列何者正確？",
    "options": {
      "A": "此乃感受寒邪四日太陰受之，故腹脹嗝氣",
      "B": "此乃兩感於寒，陽明與太陰俱病，故頭痛、腹脹滿、嗝氣",
      "C": "此乃病邪稍退但熱未盡，與水穀之氣相薄，兩熱相合所致",
      "D": "此乃傷食之後復感外邪所致"
    },
    "answer": "C",
    "category": "內經"
  },
  {
    "question": "60 歲男性患者，發燒攝氏 39.5 度且有煩心滿悶狀已 2 日，服藥後身汗出但仍然煩心滿悶不舒。依《素問．評熱病論》其可能之致病病機，下列何者正確？",
    "options": {
      "A": "陰陽交",
      "B": "腎風",
      "C": "風厥",
      "D": "勞風"
    },
    "answer": "C",
    "category": "內經"
  },
  {
    "question": "對於各臟腑之咳嗽表現，若咳嗽不已，依《素問．咳論》的描述，可能產生的變化，下列何者正確？",
    "options": {
      "A": "脾咳不已，之後會出現咳嘔膽汁",
      "B": "腎咳不已，之後會出現面目浮腫",
      "C": "肝咳不已，之後會出現右脅下痛",
      "D": "肺咳不已，之後會出現咳而遺失（矢）"
    },
    "answer": "D",
    "category": "內經"
  },
  {
    "question": "依《難經．四十九難》所論，病有正經自病與五邪所傷。假令心病，中濕得之，其症狀之論述，下列何者錯誤？",
    "options": {
      "A": "身熱小腹痛",
      "B": "足脛寒而逆",
      "C": "汗出不可止",
      "D": "身熱體重嗜臥"
    },
    "answer": "D",
    "category": "難經"
  },
  {
    "question": "王先生早上突然腹脹滿，大便泄瀉如水注，食即嘔吐逆。依《難經．五十七難》所述為下列何者之表現？",
    "options": {
      "A": "大腸泄",
      "B": "脾泄",
      "C": "胃泄",
      "D": "大瘕泄"
    },
    "answer": "B",
    "category": "難經"
  },
  {
    "question": "關於「痿躄」，主要症狀是身體軟弱、四肢無力，舉動不能，有五臟的區別。張景岳論述，認為五臟之痿，皆是因何臟氣熱，而生痿躄？",
    "options": {
      "A": "心氣熱",
      "B": "肺氣熱",
      "C": "脾氣熱",
      "D": "肝氣熱"
    },
    "answer": "B",
    "category": "難經"
  },
  {
    "question": "關於《素問．厥論》中「厥」的敘述，下列何者錯誤？",
    "options": {
      "A": "巨陽之厥，則腫首頭重，足不能行，發為眴仆",
      "B": "陽明之厥，則癲疾欲走呼，腹滿不得臥，面赤而熱，妄見而妄言",
      "C": "太陰之厥，則口乾溺赤，腹滿心痛",
      "D": "厥陰之厥，則少腹腫痛，腹脹，涇溲不利，好臥屈膝，陰縮腫，胻內熱"
    },
    "answer": "C",
    "category": "難經"
  },
  {
    "question": "關於《素問．瘧論》中關於瘧證的病名與敘述，下列何者錯誤？",
    "options": {
      "A": "先傷於寒，後傷於熱，……，名曰痎瘧",
      "B": "先傷於寒，後傷於風，……，名曰寒瘧",
      "C": "先傷於風，而後傷於寒，……，名曰溫瘧",
      "D": "但熱而不寒者，……，則少氣煩寃，手足熱而欲嘔，名曰癉瘧"
    },
    "answer": "A",
    "category": "難經"
  },
   {
    "question": "張先生搬重後起身困難，腰痛連右側臀部至大、小腿後側痛，甚至右足大拇指麻木刺痛感，咳嗽或如廁皆會造成疼痛加劇。張太太則是感覺疲倦及記憶力變差，有時左側肩膀，有時右側大腿痠痛休作不定。張先生和張太太依《內經》所述，分別罹患下列何種痹症？",
    "options": {
      "A": "骨痹；筋痹",
      "B": "腎痹；脾痹",
      "C": "周痹；眾痹",
      "D": "行痹；著痹"
    },
    "answer": "C",
    "category": "內經"
  },
  {
    "question": "張先生搬重後起身困難，腰痛連右側臀部至大、小腿後側痛，甚至右足大拇指麻木刺痛感，咳嗽或如廁皆會造成疼痛加劇。張太太則是感覺疲倦及記憶力變差，有時左側肩膀，有時右側大腿痠痛休作不定，關於張先生和張太太的病證，下列敘述何者最適宜？",
    "options": {
      "A": "張先生病邪在血脈之中，採循脈之分針刺原則",
      "B": "張太太病邪在脾胃之中，採獨取陽明，兼取五臟俞穴之法",
      "C": "張先生病邪在骨髓之中，採揚刺法，散結止痛",
      "D": "張太太病邪在分肉之中，採繆刺法"
    },
    "answer": "A",
    "category": "內經"
  },
  {
    "question": "依《素問．熱論》，有關「兩感於寒」的症狀表現，下列敘述何者正確？",
    "options": {
      "A": "囊縱，少腹微下，大氣皆去",
      "B": "腹滿而吐，食不下，自利益甚",
      "C": "渴止不滿，舌乾已而嚏",
      "D": "頭痛、口乾而煩滿"
    },
    "answer": "D",
    "category": "內經"
  },
  {
    "question": "依《靈樞．玉版》，有關癰疽之治療預後，因治療不當造成的逆證表現，下列敘述何者正確？",
    "options": {
      "A": "白眼青，黑眼大",
      "B": "服藥而嘔",
      "C": "腹脹少便",
      "D": "膿潰腫消"
    },
    "answer": "B",
    "category": "內經"
  },
  {
    "question": "依《素問．舉痛論》，有關引起痛的病因病機，下列何者錯誤？",
    "options": {
      "A": "寒氣客於腸胃之間，膜原之下，血不得散，小絡急引故痛",
      "B": "寒氣客於大腸，大腸不得成聚，故後泄腹痛矣",
      "C": "寒氣客於背俞之脈則脈泣，脈泣則血虛，血虛則痛",
      "D": "熱氣留於小腸，腸中痛，癉熱焦渴則堅乾不得出，故痛而閉不通矣"
    },
    "answer": "B",
    "category": "內經"
  }












   
]